[{"id":"3af82246.3634ae","type":"tab","label":"Flow 1","disabled":false,"info":""},{"id":"d3b28573.422e18","type":"inject","z":"3af82246.3634ae","name":"","props":[{"p":"payload"},{"p":"topic","vt":"str"}],"repeat":"","crontab":"","once":false,"onceDelay":0.001,"topic":"","payload":"","payloadType":"date","x":410,"y":300,"wires":[["37d2bb8f.f4f9b4"]]},{"id":"37d2bb8f.f4f9b4","type":"debug","z":"3af82246.3634ae","name":"","active":true,"tosidebar":true,"console":false,"tostatus":false,"complete":"false","statusVal":"","statusType":"auto","x":680,"y":320,"wires":[]}]
